pbq/__init__.py
pbq/pbq.py
pbq/query.py
pbq-0.1.8.dist-info/AUTHORS.rst
pbq-0.1.8.dist-info/LICENSE
pbq-0.1.8.dist-info/METADATA
pbq-0.1.8.dist-info/WHEEL
pbq-0.1.8.dist-info/top_level.txt
pbq-0.1.8.dist-info/RECORD
