Metadata-Version: 2.1
Name: pbq
Version: 0.1.8
Summary: python bigquery driver for easy access
Home-page: https://github.com/amirdor/pbq
Author: Dor Amir
Author-email: amirdor@gmail.com
License: MIT license
Keywords: pbq
Platform: UNKNOWN
Classifier: Development Status :: 2 - Pre-Alpha
Classifier: Intended Audience :: Developers
Classifier: License :: OSI Approved :: MIT License
Classifier: Natural Language :: English
Classifier: Programming Language :: Python :: 2
Classifier: Programming Language :: Python :: 2.7
Classifier: Programming Language :: Python :: 3
Classifier: Programming Language :: Python :: 3.5
Classifier: Programming Language :: Python :: 3.6
Classifier: Programming Language :: Python :: 3.7
Requires-Python: >=2.7, !=3.0.*, !=3.1.*, !=3.2.*, !=3.3.*, !=3.4.*
Requires-Dist: google-api-core (==1.14.*)
Requires-Dist: google-cloud-bigquery-storage (==0.7.*)
Requires-Dist: google-cloud-bigquery (==1.20.*)
Requires-Dist: google-cloud-core (==1.0.*)
Requires-Dist: pandas (==0.25.*)
Requires-Dist: pyarrow (==0.14.*)
Requires-Dist: fastparquet (==0.3.*)
Requires-Dist: requests (==2.22.*)
